swarmauri_vectorstore_tfidf/TfidfVectorStore.py
swarmauri_vectorstore_tfidf/__init__.py
swarmauri_vectorstore_tfidf-0.6.1.dist-info/LICENSE
swarmauri_vectorstore_tfidf-0.6.1.dist-info/METADATA
swarmauri_vectorstore_tfidf-0.6.1.dist-info/WHEEL
swarmauri_vectorstore_tfidf-0.6.1.dist-info/entry_points.txt
swarmauri_vectorstore_tfidf-0.6.1.dist-info/RECORD
