Metadata-Version: 2.3
Name: swarmauri_vectorstore_tfidf
Version: 0.6.1
Summary: A Tfidf based Vector Store and Tfidf Based Embedding Model.
License: Apache-2.0
Author: Jacob Stewart
Author-email: jacob@swarmauri.com
Requires-Python: >=3.10,<3.13
Classifier: License :: OSI Approved :: Apache Software License
Classifier: Programming Language :: Python :: 3
Classifier: Programming Language :: Python :: 3.10
Classifier: Programming Language :: Python :: 3.11
Classifier: Programming Language :: Python :: 3.12
Requires-Dist: swarmauri_base (>=0.6.1,<0.7.0)
Requires-Dist: swarmauri_core (>=0.6.1,<0.7.0)
Requires-Dist: swarmauri_embedding_tfidf (>=0.6.1,<0.7.0)
Requires-Dist: swarmauri_standard (>=0.6.1,<0.7.0)
Project-URL: Repository, http://github.com/swarmauri/swarmauri-sdk
